oidc/__init__.py
oidc/apps.py
oidc/constants.py
oidc/provider.py
oidc/templates/oidc/configure.html
oidc/views.py
muxa1l_sentry_auth_oidc-5.0.5.dist-info/entry_points.txt
muxa1l_sentry_auth_oidc-5.0.5.dist-info/LICENSE
muxa1l_sentry_auth_oidc-5.0.5.dist-info/WHEEL
muxa1l_sentry_auth_oidc-5.0.5.dist-info/METADATA
muxa1l_sentry_auth_oidc-5.0.5.dist-info/RECORD
