Metadata-Version: 2.1
Name: muxa1l-sentry-auth-oidc
Version: 5.0.5
Summary: OpenID Connect authentication provider for Sentry
Author: Max Wittig
Author-email: max.wittig@siemens.com
Requires-Python: >=3.6,<4.0
Classifier: Intended Audience :: Developers
Classifier: Intended Audience :: System Administrators
Classifier: Operating System :: OS Independent
Classifier: Programming Language :: Python :: 3
Classifier: Programming Language :: Python :: 3.6
Classifier: Programming Language :: Python :: 3.7
Classifier: Programming Language :: Python :: 3.8
Classifier: Topic :: Software Development
